{
    "self-portrait": {
        "basic_information": {
            "id": "",
            "name": "",
            "en_name": "",
            "age": "",
            "gender": "",
            "martial_status": "",
            "occupation": ""
        },
        "diagnosis": {
            "symptoms": "",
            "status": "",
            "drisk": "",
            "srisk": "",
            "reason": ""
        },
        "character": [
            "内向",
            "敏感",
            "自卑",
            "焦虑",
            "缺乏自信",
            "容易疲惫",
            "决断力差"
        ],
        "appearance": [
            "中等身高",
            "瘦弱",
            "面色苍白",
            "眼神疲惫",
            "头发略显凌乱"
        ],
        "interests_and_hobbies": {
            "hobbies": [
                "阅读",
                "听音乐",
                "绘画"
            ],
            "activity": [
                "独自一人听音乐",
                "在安静的地方阅读",
                "偶尔尝试绘画"
            ]
        },
        "dreams_and_aspirations": {
            "short_term_goals": "顺利完成论文并毕业",
            "long_term_goals": "找到一份稳定的工作，能够自立"
        },
        "daily_life": {
            "routine": "每天早上被闹钟吵醒，通常会在床上躺一会儿才起床。白天大部分时间在图书馆或宿舍里写论文，但效率很低。晚上会尝试早睡，但通常需要两小时才能入睡。",
            "weekends": "周末通常会待在宿舍，偶尔会去校园里的安静角落阅读或听音乐。很少与同学交流，更多时间是独自一人。"
        },
        "past_experiences": {
            "childhood": "小时候性格活泼，但在小学高年级时因成绩下滑受到老师和家长的批评，逐渐变得内向。",
            "adolescence": "中学时期成绩一般，常常感到压力大，尤其在高考前后。进入大学后，因学业压力和导师的严格要求，逐渐感到自信心下降。",
            "recent_events": "最近两个月因论文多次被退回，情绪低落，睡眠质量差，感到未来迷茫。"
        },
        "environment": "出生在一个小城市，家庭经济条件一般。大学在大城市就读，远离家乡，缺乏亲友的支持。"
    },
    "social-portrait": {
        "social_connections_closeness": {
            "childhood": [
                {
                    "relationship": "父亲",
                    "count": 1,
                    "familiarity": [
                        4
                    ],
                    "description": [
                        "周琰可的父亲是一名工人，工作繁忙，但对她的学业非常关心。小时候，父亲常常在她成绩下滑时给予严厉的批评，这让她逐渐变得内向。"
                    ]
                },
                {
                    "relationship": "母亲",
                    "count": 1,
                    "familiarity": [
                        5
                    ],
                    "description": [
                        "周琰可的母亲是一名家庭主妇，性格温和。母亲在她小时候给予了很多关爱，但在学业上也有很高的期望。母亲的温柔和期望让她感到既温暖又有压力。"
                    ]
                },
                {
                    "relationship": "朋友",
                    "count": 2,
                    "familiarity": [
                        3,
                        3
                    ],
                    "description": [
                        "周琰可在小学时有两个好朋友，她们常常一起玩耍，但在成绩下滑后，她逐渐疏远了这些朋友。"
                    ]
                }
            ],
            "adolescence": [
                {
                    "relationship": "同学",
                    "count": 5,
                    "familiarity": [
                        2,
                        2,
                        2,
                        2,
                        2
                    ],
                    "description": [
                        "中学时期，周琰可的同学们大多是竞争对手，她感到压力很大，难以与他们建立深厚的友谊。"
                    ]
                },
                {
                    "relationship": "老师",
                    "count": 3,
                    "familiarity": [
                        3,
                        3,
                        3
                    ],
                    "description": [
                        "中学老师对她的期望很高，但也常常批评她的表现，这让她感到自信心下降。"
                    ]
                }
            ],
            "recent_events": [
                {
                    "relationship": "导师",
                    "count": 1,
                    "familiarity": [
                        2
                    ],
                    "description": [
                        "周琰可的导师对她的论文要求严格，但缺乏具体指导，这让她感到非常困惑和无助。"
                    ]
                },
                {
                    "relationship": "同学",
                    "count": 3,
                    "familiarity": [
                        2,
                        2,
                        2
                    ],
                    "description": [
                        "大学同学们大多忙于自己的学业，周琰可很少与他们交流，感到孤独。"
                    ]
                },
                {
                    "relationship": "心理咨询师",
                    "count": 1,
                    "familiarity": [
                        3
                    ],
                    "description": [
                        "最近，周琰可开始与心理咨询师交流，虽然她感到决断力差，但咨询师的建议让她感到一丝希望。"
                    ]
                }
            ]
        },
        "social_connections_change": "周琰可在不同阶段的社会关系发生了显著变化。小时候，她有父母的关爱和朋友的陪伴，但在学业压力下，她逐渐变得内向，疏远了朋友。中学时期，她的社交圈子主要是同学和老师，但由于竞争压力，她难以建立深厚的友谊。进入大学后，远离家乡的她感到孤独，缺乏亲友的支持，社交圈子变得更加狭窄。最近，她开始寻求心理咨询师的帮助，虽然感到决断力差，但这也为她的社交关系带来了一丝新的变化和希望。"
    }
}