{
    "self-portrait": {
        "basic_information": {
            "id": "",
            "name": "",
            "en_name": "",
            "age": "",
            "gender": "",
            "martial_status": "",
            "occupation": ""
        },
        "diagnosis": {
            "symptoms": "",
            "status": "",
            "drisk": "",
            "srisk": "",
            "reason": ""
        },
        "character": [
            "善良",
            "关心",
            "认真",
            "有责任心",
            "内向"
        ],
        "appearance": [
            "中等身高",
            "瘦削",
            "黑发",
            "戴眼镜",
            "温和的面容"
        ],
        "interests_and_hobbies": {
            "hobbies": [
                "阅读",
                "写作",
                "园艺",
                "烹饪"
            ],
            "activity": [
                "和家人一起做饭",
                "周末去公园散步",
                "参加读书会"
            ]
        },
        "dreams_and_aspirations": {
            "short_term_goals": "改善睡眠质量，减轻工作压力",
            "long_term_goals": "成为一名优秀的教育工作者，帮助更多的学生成长"
        },
        "daily_life": {
            "routine": "每天早上6点起床，准备早餐后去学校。白天上课和批改作业，下午4点左右回家。晚上备课和阅读，10点左右上床休息。",
            "weekends": "周末通常会和家人一起做饭，去公园散步，或者参加读书会。偶尔会进行一些园艺活动，放松心情。"
        },
        "past_experiences": {
            "childhood": "出生在一个普通的工薪家庭，父母都是工人。小时候成绩优异，喜欢阅读和写作。",
            "adolescence": "中学时期成绩依然优秀，参加了学校的文学社，发表了一些文章。",
            "youth": "大学期间选择了师范专业，毕业后成为了一名初中教师。结婚后生活稳定，但工作压力逐渐增大。",
            "recent_events": "最近所带班级进入初三，工作压力骤增，导致睡眠问题和疲倦感。"
        },
        "environment": "出生在江苏省南京市，在这里上了小学和中学。大学在南京师范大学就读，毕业后留在南京工作和生活。"
    },
    "social-portrait": {
        "social_connections_closeness": {
            "childhood": [
                {
                    "relationship": "父母",
                    "count": 2,
                    "familiarity": [
                        5,
                        5
                    ],
                    "description": [
                        "罗纯茜的父母都是工人，虽然工作忙碌，但他们对罗纯茜的教育非常重视。父母经常鼓励她阅读和写作，给了她很大的支持和爱。"
                    ]
                },
                {
                    "relationship": "朋友",
                    "count": 3,
                    "familiarity": [
                        4,
                        4,
                        3
                    ],
                    "description": [
                        "罗纯茜在小学时有几个好朋友，他们经常一起玩耍和学习。虽然后来因为升学分开了，但这些童年的友谊对她来说非常珍贵。"
                    ]
                }
            ],
            "adolescence": [
                {
                    "relationship": "父母",
                    "count": 2,
                    "familiarity": [
                        5,
                        5
                    ],
                    "description": [
                        "在中学时期，罗纯茜的父母依然是她最坚实的后盾。虽然他们对她的期望很高，但也给予了她足够的自由去追求自己的兴趣。"
                    ]
                },
                {
                    "relationship": "文学社成员",
                    "count": 5,
                    "familiarity": [
                        4,
                        4,
                        3,
                        3,
                        3
                    ],
                    "description": [
                        "罗纯茜在中学时期加入了学校的文学社，结识了一群志同道合的朋友。他们一起讨论文学，互相鼓励，成为了她重要的社交圈子。"
                    ]
                }
            ],
            "youth": [
                {
                    "relationship": "大学同学",
                    "count": 4,
                    "familiarity": [
                        4,
                        4,
                        3,
                        3
                    ],
                    "description": [
                        "在南京师范大学期间，罗纯茜结识了一些好朋友，他们一起学习、生活，共同度过了大学时光。这些友谊在她毕业后依然保持着。"
                    ]
                },
                {
                    "relationship": "丈夫",
                    "count": 1,
                    "familiarity": [
                        5
                    ],
                    "description": [
                        "罗纯茜在大学期间认识了她的丈夫，他们相互支持，共同面对生活中的挑战。结婚后，丈夫成为了她最亲密的伙伴和支持者。"
                    ]
                }
            ],
            "recent_events": [
                {
                    "relationship": "同事",
                    "count": 6,
                    "familiarity": [
                        4,
                        4,
                        3,
                        3,
                        3,
                        3
                    ],
                    "description": [
                        "作为一名初中教师，罗纯茜与同事们保持着良好的关系。他们经常交流教学经验，互相支持，共同面对工作中的压力。"
                    ]
                },
                {
                    "relationship": "学生",
                    "count": 30,
                    "familiarity": [
                        3,
                        3,
                        3,
                        3,
                        3,
                        3,
                        3,
                        3,
                        3,
                        3,
                        3,
                        3,
                        3,
                        3,
                        3,
                        3,
                        3,
                        3,
                        3,
                        3,
                        3,
                        3,
                        3,
                        3,
                        3,
                        3,
                        3,
                        3,
                        3,
                        3
                    ],
                    "description": [
                        "罗纯茜非常关心她的学生，尽管工作压力大，但她依然尽力帮助每一个学生成长。学生们也非常尊敬和喜欢她。"
                    ]
                },
                {
                    "relationship": "家人",
                    "count": 3,
                    "familiarity": [
                        5,
                        5,
                        4
                    ],
                    "description": [
                        "罗纯茜的家人，包括她的丈夫和两个孩子，是她生活中最重要的支持系统。尽管工作繁忙，她依然尽量抽出时间陪伴家人。"
                    ]
                }
            ]
        },
        "social_connections_change": "罗纯茜的社交圈子随着时间的推移发生了变化。从童年时期的家庭和朋友，到中学时期的文学社成员，再到大学时期的同学和丈夫，以及现在的同事和学生。尽管她的社交圈子在不断变化，但她始终保持着对人际关系的重视和关心。最近，由于工作压力大，她的社交活动有所减少，但她依然尽力保持与家人和朋友的联系。"
    }
}