{
    "self-portrait": {
        "basic_information": {
            "id": "",
            "name": "",
            "en_name": "",
            "age": "",
            "gender": "",
            "martial_status": "",
            "occupation": ""
        },
        "diagnosis": {
            "symptoms": "",
            "status": "",
            "drisk": "",
            "srisk": "",
            "reason": ""
        },
        "character": [
            "内向",
            "敏感",
            "缺乏自信",
            "犹豫不决",
            "容易焦虑",
            "渴望被理解"
        ],
        "appearance": [
            "中等身高",
            "瘦弱",
            "皮肤苍白",
            "眼神疲惫",
            "头发略显凌乱"
        ],
        "interests_and_hobbies": {
            "hobbies": [
                "阅读",
                "听音乐",
                "绘画"
            ],
            "activity": [
                "独自散步",
                "在图书馆安静地待着"
            ]
        },
        "dreams_and_aspirations": {
            "short_term_goals": "能够恢复正常的睡眠，提升学习效率",
            "long_term_goals": "找到自己真正的兴趣和方向，建立稳定的人际关系"
        },
        "daily_life": {
            "routine": "早上起床后感到疲倦，勉强去上课，但注意力难以集中。下午通常在图书馆或宿舍待着，晚上难以入睡，经常做噩梦。",
            "weekends": "周末大部分时间在宿舍休息，偶尔会去图书馆或校园内散步，但很少与人交流。"
        },
        "past_experiences": {
            "childhood": "小时候性格活泼，但在小学高年级时因成绩压力逐渐变得内向。",
            "adolescence": "中学时期因学业压力和人际关系问题，逐渐出现焦虑和抑郁的症状。",
            "recent_events": "进入大学后，因适应新环境和学业压力，抑郁症状加重，开始频繁做噩梦，注意力难以集中。"
        },
        "environment": "出生在一个小城市，家庭经济条件一般，父母对她的期望很高。高中毕业后考入省会城市的一所大学，但因适应不良和学业压力，抑郁症状加重。"
    },
    "social-portrait": {
        "social_connections_closeness": {
            "childhood": [
                {
                    "relationship": "父亲",
                    "count": 1,
                    "familiarity": [
                        4
                    ],
                    "description": [
                        "傅香纨的父亲是一位严肃但关心她的人。小时候，父亲常常陪她做作业，但随着她成绩压力的增加，父亲的期望也变得更高，导致她感到压力。"
                    ]
                },
                {
                    "relationship": "母亲",
                    "count": 1,
                    "familiarity": [
                        5
                    ],
                    "description": [
                        "母亲是傅香纨的主要情感支持者。她温柔且耐心，常常在傅香纨感到压力时安慰她。母亲对她的期望也很高，但更多的是希望她能快乐。"
                    ]
                },
                {
                    "relationship": "朋友",
                    "count": 3,
                    "familiarity": [
                        3,
                        3,
                        4
                    ],
                    "description": [
                        "傅香纨小时候有几个好朋友，她们常常一起玩耍和学习。但随着年级的升高，学业压力增加，她与朋友们的关系逐渐疏远。"
                    ]
                }
            ],
            "adolescence": [
                {
                    "relationship": "父亲",
                    "count": 1,
                    "familiarity": [
                        3
                    ],
                    "description": [
                        "进入中学后，傅香纨与父亲的关系变得紧张。父亲对她的成绩要求更高，导致她感到压力和焦虑。"
                    ]
                },
                {
                    "relationship": "母亲",
                    "count": 1,
                    "familiarity": [
                        4
                    ],
                    "description": [
                        "母亲依然是她的情感支柱，但由于学业压力，傅香纨与母亲的交流也减少了。"
                    ]
                },
                {
                    "relationship": "朋友",
                    "count": 2,
                    "familiarity": [
                        2,
                        3
                    ],
                    "description": [
                        "中学时期，傅香纨的朋友数量减少了。她与几个朋友保持联系，但由于焦虑和抑郁，她逐渐与他们疏远。"
                    ]
                },
                {
                    "relationship": "老师",
                    "count": 1,
                    "familiarity": [
                        3
                    ],
                    "description": [
                        "傅香纨有一位特别关心她的老师，这位老师注意到她的情绪变化，常常鼓励她，但效果有限。"
                    ]
                }
            ],
            "recent_events": [
                {
                    "relationship": "父亲",
                    "count": 1,
                    "familiarity": [
                        2
                    ],
                    "description": [
                        "进入大学后，傅香纨与父亲的关系更加疏远。父亲对她的期望依然很高，但她感到自己无法达到这些期望。"
                    ]
                },
                {
                    "relationship": "母亲",
                    "count": 1,
                    "familiarity": [
                        3
                    ],
                    "description": [
                        "母亲依然关心她，但由于距离和学业压力，傅香纨与母亲的交流减少了。"
                    ]
                },
                {
                    "relationship": "朋友",
                    "count": 1,
                    "familiarity": [
                        2
                    ],
                    "description": [
                        "大学里，傅香纨结交了一个朋友，但由于她的抑郁症状，这段友谊也变得不稳定。"
                    ]
                },
                {
                    "relationship": "心理咨询师",
                    "count": 1,
                    "familiarity": [
                        4
                    ],
                    "description": [
                        "傅香纨与心理咨询师的关系较为顺畅，她在咨询师面前能够表达自己的感受，但依然感到迷茫和无助。"
                    ]
                }
            ]
        },
        "social_connections_change": "傅香纨的社会关系在不同阶段发生了显著变化。小时候，她有较多的朋友和家庭支持，但随着学业压力的增加，她逐渐与朋友和家人疏远。进入大学后，她的抑郁症状加重，导致她的人际关系更加不稳定。她渴望被理解和支持，但由于缺乏自信和焦虑，她难以建立和维持稳定的社会关系。"
    }
}