{
    "self-portrait": {
        "basic_information": {
            "id": "",
            "name": "",
            "en_name": "",
            "age": "",
            "gender": "",
            "martial_status": "",
            "occupation": ""
        },
        "diagnosis": {
            "symptoms": "",
            "status": "",
            "drisk": "",
            "srisk": "",
            "reason": ""
        },
        "character": [
            "善良",
            "关心",
            "诚实",
            "慢热",
            "有责任心"
        ],
        "appearance": [
            "中等身高",
            "苗条",
            "清秀",
            "温和的眼神"
        ],
        "interests_and_hobbies": {
            "hobbies": [
                "教书",
                "跑步",
                "阅读",
                "听音乐"
            ],
            "activity": [
                "和朋友一起跑步",
                "周末去图书馆",
                "听音乐放松"
            ]
        },
        "dreams_and_aspirations": {
            "short_term_goals": "适应新学校的环境，找到有效的班级管理方法",
            "long_term_goals": "成为一名优秀的教师，能够影响和帮助更多的学生"
        },
        "daily_life": {
            "routine": "每天早上6点起床，跑步半小时后准备早餐。7点半到学校，开始一天的教学工作。下午放学后，整理教案和批改作业。晚上9点左右休息。",
            "weekends": "周末会去图书馆阅读，或者和朋友一起跑步。偶尔会和家人一起做饭，享受家庭时光。"
        },
        "past_experiences": {
            "childhood": "出生在一个普通的家庭，父母都是工薪阶层。从小喜欢阅读和学习，成绩一直很好。",
            "adolescence": "中学时期成绩优异，曾担任班长，积极参与学校的各种活动。高中毕业后考入师范大学。",
            "recent_events": "刚刚毕业并进入一所新的初中任教，面对学生的叛逆期和新的工作环境，感到有些迷茫和困惑。"
        },
        "environment": "出生在一个小城市，家庭氛围温馨和睦。大学期间在省会城市读书，毕业后回到家乡的初中任教。"
    },
    "social-portrait": {
        "social_connections_closeness": {
            "childhood": [
                {
                    "relationship": "父亲",
                    "count": 1,
                    "familiarity": [
                        5
                    ],
                    "description": [
                        "罗贞莺的父亲是一名工薪阶层，工作稳定，性格温和。他在罗贞莺的成长过程中给予了她很多支持和鼓励，尤其是在她的学业上。父女关系非常亲密，罗贞莺从小就喜欢和父亲分享她的读书心得和学习成果。"
                    ]
                },
                {
                    "relationship": "母亲",
                    "count": 1,
                    "familiarity": [
                        5
                    ],
                    "description": [
                        "罗贞莺的母亲是一名家庭主妇，性格开朗，善于沟通。她在家庭中扮演着重要的角色，照顾家庭的日常生活。母女关系非常亲密，罗贞莺从小就喜欢和母亲一起做家务和烹饪。"
                    ]
                },
                {
                    "relationship": "朋友",
                    "count": 2,
                    "familiarity": [
                        4,
                        4
                    ],
                    "description": [
                        "罗贞莺在小学时期有两个非常要好的朋友，他们经常一起玩耍和学习。这些朋友在她的成长过程中给予了她很多陪伴和支持。"
                    ]
                }
            ],
            "adolescence": [
                {
                    "relationship": "班主任",
                    "count": 1,
                    "familiarity": [
                        4
                    ],
                    "description": [
                        "罗贞莺的中学班主任是一位非常严格但关心学生的老师。在她的指导下，罗贞莺不仅在学业上取得了优异的成绩，还学会了如何与人相处和管理时间。"
                    ]
                },
                {
                    "relationship": "同学",
                    "count": 5,
                    "familiarity": [
                        3,
                        3,
                        3,
                        3,
                        3
                    ],
                    "description": [
                        "罗贞莺在中学时期有几个关系较好的同学，他们一起参加学校的各种活动，互相帮助，共同进步。"
                    ]
                },
                {
                    "relationship": "家教老师",
                    "count": 1,
                    "familiarity": [
                        4
                    ],
                    "description": [
                        "罗贞莺在高中时期请了一位家教老师，帮助她提高学习成绩。这位老师不仅在学业上给予了她很多帮助，还在生活上给予了她很多建议和支持。"
                    ]
                }
            ],
            "recent_events": [
                {
                    "relationship": "带教师傅",
                    "count": 1,
                    "familiarity": [
                        4
                    ],
                    "description": [
                        "罗贞莺刚进入新学校时，学校安排了一位带教师傅帮助她适应新的工作环境。这位带教师傅经验丰富，给予了罗贞莺很多指导和支持。"
                    ]
                },
                {
                    "relationship": "同事",
                    "count": 3,
                    "familiarity": [
                        3,
                        3,
                        3
                    ],
                    "description": [
                        "罗贞莺在新学校有几位关系较好的同事，他们经常一起讨论教学方法和班级管理经验。"
                    ]
                },
                {
                    "relationship": "学生",
                    "count": 30,
                    "familiarity": [
                        2,
                        2,
                        2,
                        2,
                        2,
                        2,
                        2,
                        2,
                        2,
                        2,
                        2,
                        2,
                        2,
                        2,
                        2,
                        2,
                        2,
                        2,
                        2,
                        2,
                        2,
                        2,
                        2,
                        2,
                        2,
                        2,
                        2,
                        2,
                        2,
                        2
                    ],
                    "description": [
                        "罗贞莺目前管理一个初中班级，班里有30名学生。虽然学生们正处于叛逆期，但她努力与他们建立良好的师生关系。"
                    ]
                }
            ]
        },
        "social_connections_change": "罗贞莺在不同阶段的社会关系中，逐渐从家庭和朋友的支持转向职业和同事的支持。她在成长过程中学会了如何与不同的人相处，并在新的工作环境中逐渐适应和建立新的社会关系。虽然她目前感到迷茫和困惑，但她相信通过自己的努力和同事的帮助，能够逐渐适应新的工作环境，找到有效的班级管理方法。"
    }
}